izaax/__init__.py
izaax/bot.py
izaax/cli.py
izaax/client.py
izaax/item.py
izaax/utils.py
izaax-0.1.0.dist-info/LICENSE
izaax-0.1.0.dist-info/METADATA
izaax-0.1.0.dist-info/WHEEL
izaax-0.1.0.dist-info/entry_points.txt
izaax-0.1.0.dist-info/RECORD
