Metadata-Version: 2.1
Name: izaax
Version: 0.1.0
Summary: 
Author: narumi
Author-email: toucans-cutouts0f@icloud.com
Requires-Python: >=3.10,<4.0
Classifier: Programming Language :: Python :: 3
Classifier: Programming Language :: Python :: 3.10
Classifier: Programming Language :: Python :: 3.11
Classifier: Programming Language :: Python :: 3.12
Requires-Dist: beautifulsoup4 (>=4.12.3,<5.0.0)
Requires-Dist: feedparser (>=6.0.11,<7.0.0)
Requires-Dist: httpx (>=0.27.0,<0.28.0)
Requires-Dist: pydantic (>=2.6.4,<3.0.0)
Requires-Dist: python-dotenv (>=1.0.1,<2.0.0)
Requires-Dist: python-telegram-bot (>=21.0.1,<22.0.0)
Requires-Dist: redis (>=5.0.3,<6.0.0)
